pydsol/model/__init__.py
pydsol/model/basic_logger.py
pydsol/model/entities.py
pydsol/model/link.py
pydsol/model/node.py
pydsol/model/queue_model.py
pydsol/model/resource.py
pydsol/model/server.py
pydsol/model/sink.py
pydsol/model/source.py
pydsol_model-1.0.0.dist-info/LICENSE
pydsol_model-1.0.0.dist-info/METADATA
pydsol_model-1.0.0.dist-info/WHEEL
pydsol_model-1.0.0.dist-info/top_level.txt
pydsol_model-1.0.0.dist-info/RECORD
