Metadata-Version: 2.1
Name: pydsol-model
Version: 1.0.0
Summary: Predefined objects library for a Python discrete-event simulation model (pydsol-core)
Home-page: https://github.com/imvs95/pydsol-model
Author: Isabelle M. van Schilt
Author-email: Isabelle van Schilt <isabellevanschilt@gmail.com>
License: BSD 3-Clause License
Project-URL: documentation, https://pydsol-model.readthedocs.io/en/latest/index.html
Project-URL: repository, https://github.com/imvs95/pydsol-model
Keywords: simulation,discrete-event,model
Classifier: License :: OSI Approved :: BSD License
Classifier: Programming Language :: Python
Classifier: Programming Language :: Python :: 3
Requires-Python: >=3.9
License-File: LICENSE
Requires-Dist: pydsol-core
Requires-Dist: numpy
Provides-Extra: dev
Requires-Dist: pytest ; extra == 'dev'
